databurglar/__init__.py
databurglar/calculators/__init__.py
databurglar/calculators/base.py
databurglar/calculators/services.py
databurglar/helpers/__init__.py
databurglar/helpers/connection.py
databurglar/helpers/executors.py
databurglar/models/__init__.py
databurglar/models/base.py
databurglar/models/data.py
databurglar/models/data_store.py
databurglar/models/enums.py
databurglar/models/events.py
databurglar/models/pocos.py
databurglar/models/survey.py
databurglar/models/survey_question.py
databurglar/models/tag.py
databurglar/models/typings.py
databurglar/queries/__init__.py
databurglar/queries/data_store.py
databurglar/queries/tag.py
databurglar/services/__init__.py
databurglar/services/data_store.py
databurglar/validators/__init__.py
databurglar/validators/base.py
databurglar/validators/services.py
databurglar-0.0.3.dist-info/LICENSE
databurglar-0.0.3.dist-info/METADATA
databurglar-0.0.3.dist-info/WHEEL
databurglar-0.0.3.dist-info/top_level.txt
databurglar-0.0.3.dist-info/RECORD
