Metadata-Version: 2.1
Name: databurglar
Version: 0.0.3
Summary: SQLAlchemy Package for data tracking.
Home-page: https://github.com/dpasse/databurglar
Keywords: Data Collection,SqlAlchemy
Requires-Python: >=3.12.5
License-File: LICENSE
Requires-Dist: SQLAlchemy==2.0.32
Requires-Dist: pydantic==2.8
Requires-Dist: psycopg2==2.9.9
